libpgm/__init__.py
libpgm/dictionary.py
libpgm/discretebayesiannetwork.py
libpgm/dyndiscbayesiannetwork.py
libpgm/graphskeleton.py
libpgm/hybayesiannetwork.py
libpgm/lgbayesiannetwork.py
libpgm/nodedata.py
libpgm/orderedskeleton.py
libpgm/pgmlearner.py
libpgm/sampleaggregator.py
libpgm/tablecpdfactor.py
libpgm/tablecpdfactorization.py
libpgm/CPDtypes/__init__.py
libpgm/CPDtypes/crazy.py
libpgm/CPDtypes/discrete.py
libpgm/CPDtypes/lg.py
libpgm/CPDtypes/lgandd.py
libpgm3/__init__.py
libpgm3/dictionary.py
libpgm3/discretebayesiannetwork.py
libpgm3/dyndiscbayesiannetwork.py
libpgm3/graphskeleton.py
libpgm3/hybayesiannetwork.py
libpgm3/lgbayesiannetwork.py
libpgm3/nodedata.py
libpgm3/orderedskeleton.py
libpgm3/pgmlearner.py
libpgm3/sampleaggregator.py
libpgm3/tablecpdfactor.py
libpgm3/tablecpdfactorization.py
libpgm3/CPDtypes/__init__.py
libpgm3/CPDtypes/crazy.py
libpgm3/CPDtypes/discrete.py
libpgm3/CPDtypes/lg.py
libpgm3/CPDtypes/lgandd.py
utils/__init__.py
utils/bntextutils.py
utils/libpgmexceptions.py
bnlib-1.3.7.dist-info/LICENSE.txt
bnlib-1.3.7.dist-info/METADATA
bnlib-1.3.7.dist-info/WHEEL
bnlib-1.3.7.dist-info/top_level.txt
bnlib-1.3.7.dist-info/RECORD
