Metadata-Version: 2.1
Name: bnlib
Version: 1.3.7
Summary: A library for creating and using probabilistic graphical models. *Unofficial update to support python 3*.
Home-page: https://github.com/aleksandar-veljkovic/libpgm3
Author: Aleksandar Veljković (original author: CyberPoint International, LLC)
Classifier: Development Status :: 3 - Alpha
Classifier: Programming Language :: Python
Classifier: Programming Language :: Python :: 3
Classifier: License :: OSI Approved :: BSD License
Classifier: Topic :: Scientific/Engineering :: Mathematics
License-File: LICENSE.txt
